mopidy_spotify/__init__.py
mopidy_spotify/backend.py
mopidy_spotify/browse.py
mopidy_spotify/countries.py
mopidy_spotify/distinct.py
mopidy_spotify/ext.conf
mopidy_spotify/images.py
mopidy_spotify/library.py
mopidy_spotify/lookup.py
mopidy_spotify/playback.py
mopidy_spotify/playlists.py
mopidy_spotify/search.py
mopidy_spotify/spotify_appkey.key
mopidy_spotify/translator.py
mopidy_spotify/utils.py
mopidy_spotify/web.py
Mopidy_Spotify-4.1.1.dist-info/LICENSE
Mopidy_Spotify-4.1.1.dist-info/METADATA
Mopidy_Spotify-4.1.1.dist-info/WHEEL
Mopidy_Spotify-4.1.1.dist-info/entry_points.txt
Mopidy_Spotify-4.1.1.dist-info/top_level.txt
Mopidy_Spotify-4.1.1.dist-info/RECORD
